pywxbot/__init__.py
pywxbot-0.0.3.dist-info/LICENSE
pywxbot-0.0.3.dist-info/METADATA
pywxbot-0.0.3.dist-info/WHEEL
pywxbot-0.0.3.dist-info/top_level.txt
pywxbot-0.0.3.dist-info/RECORD
